{
  "chaos_orb_release_energy": {
    "subtitle": "subtitles.chaosmod.chaos_orb_release_energy",
    "sounds": [
      "chaosmod:chaos_orb_impact"
    ]
  },
  "chaos_orb_dash": {
    "subtitle": "subtitles.chaosmod.chaos_orb_dash",
    "sounds": [
      "chaosmod:chaos_orb_dash"
    ]
  },
  "chaos_orb_protect": {
    "subtitle": "subtitles.chaosmod.chaos_orb_protect",
    "sounds": [
      "chaosmod:chaos_orb_protect"
    ]
  },
  "chaos_orb_disappear": {
    "subtitle": "subtitles.chaosmod.chaos_orb_disappear",
    "sounds": [
      "chaosmod:chaos_orb_disappear"
    ]
  }
}

